asyncCommunication/__init__.py
asyncCommunication/requestHandler.py
asyncCommunication-1.1.3.dist-info/METADATA
asyncCommunication-1.1.3.dist-info/WHEEL
asyncCommunication-1.1.3.dist-info/top_level.txt
asyncCommunication-1.1.3.dist-info/RECORD
