Metadata-Version: 2.1
Name: asyncCommunication
Version: 1.1.3
Summary: A library for handling HTTP requests with base64 encoding
Home-page: https://github.com/yourusername/my_python_library
Author: Your Name
Author-email: your.email@example.com
Classifier: Programming Language :: Python :: 3
Classifier: License :: OSI Approved :: MIT License
Classifier: Operating System :: OS Independent
Requires-Python: >=3.6
Requires-Dist: requests
